litex_kernel/__init__.py
litex_kernel/__main__.py
litex_kernel/install.py
litex_kernel/kernel.py
litex_kernel/resources/__init__.py
litex_kernel/resources/logo-svg.svg
litex_kernel-1.0.1.dist-info/licenses/LICENSE
litex_kernel-1.0.1.dist-info/WHEEL
litex_kernel-1.0.1.dist-info/METADATA
litex_kernel-1.0.1.dist-info/RECORD
