Metadata-Version: 2.4
Name: litex_kernel
Version: 1.0.1
Summary: A Jupyter kernel for Litex core
Author-email: Hill Hong <scanfandprintf@icloud.com>
Requires-Python: >=3.9
License-Expression: MIT
Classifier: Framework :: Jupyter
Classifier: Programming Language :: Python :: 3
Classifier: Intended Audience :: Science/Research
Classifier: Topic :: Scientific/Engineering :: Mathematics
License-File: LICENSE
Project-URL: Homepage, https://github.com/litexlang/litex-jupyter-kernel
Project-URL: Issues, https://github.com/litexlang/litex-jupyter-kernel/issues
